jellyfin_letterboxd_sync.py
jellyfin_letterboxd_sync-0.1.4.dist-info/METADATA
jellyfin_letterboxd_sync-0.1.4.dist-info/WHEEL
jellyfin_letterboxd_sync-0.1.4.dist-info/entry_points.txt
jellyfin_letterboxd_sync-0.1.4.dist-info/top_level.txt
jellyfin_letterboxd_sync-0.1.4.dist-info/RECORD
