Metadata-Version: 2.4
Name: jellyfin-letterboxd-sync
Version: 0.1.4
Summary: Sync watched status from Jellyfin to Letterboxd
Project-URL: Homepage, https://github.com/zianwar/jellyfin-letterboxd-sync
Project-URL: Changelog, https://github.com/zianwar/jellyfin-letterboxd-sync/releases
Project-URL: Issues, https://github.com/zianwar/jellyfin-letterboxd-sync/issues
Project-URL: CI, https://github.com/zianwar/jellyfin-letterboxd-sync/actions
Requires-Python: >=3.13
Requires-Dist: httpx>=0.28.1
Requires-Dist: playwright>=1.57.0
